wrapzor/__init__.py
wrapzor/api/assignment_rules.py
wrapzor/api/blueprint.py
wrapzor/api/bulks.py
wrapzor/api/change_owner.py
wrapzor/api/contact_roles.py
wrapzor/api/currencies.py
wrapzor/api/fields_attachments.py
wrapzor/api/files.py
wrapzor/api/mass_update_records.py
wrapzor/api/meeting_cancel.py
wrapzor/api/metadata/custom_views.py
wrapzor/api/metadata/fields.py
wrapzor/api/metadata/layouts.py
wrapzor/api/metadata/related_lists.py
wrapzor/api/modules.py
wrapzor/api/notes.py
wrapzor/api/organization.py
wrapzor/api/photos_and_attachments.py
wrapzor/api/pipelines.py
wrapzor/api/profiles.py
wrapzor/api/records.py
wrapzor/api/records_using_external_id.py
wrapzor/api/related_records.py
wrapzor/api/related_records_using_external_id.py
wrapzor/api/roles.py
wrapzor/api/scoring_rules.py
wrapzor/api/send_mails.py
wrapzor/api/share_records.py
wrapzor/api/subforms.py
wrapzor/api/tags.py
wrapzor/api/templates.py
wrapzor/api/territories.py
wrapzor/api/users.py
wrapzor/api/users_unavailability.py
wrapzor/api/utils.py
wrapzor/api/variables.py
wrapzor/api/wizards.py
wrapzor/core/api.py
wrapzor/core/credentials.py
wrapzor/core/retries.py
wrapzor/core/tokens.py
wrapzor/core/verify.py
wrapzor/env.py
wrapzor/errors.py
wrapzor/logs.py
wrapzor/models/bulks.py
wrapzor/models/generics.py
wrapzor/models/metadata/custom_views.py
wrapzor/models/metadata/fields.py
wrapzor/models/metadata/layouts.py
wrapzor/models/metadata/modules.py
wrapzor/models/metadata/related_lists.py
wrapzor/models/modules.py
wrapzor/models/tokens.py
wrapzor/utils.py
wrapzor-0.1.24.dist-info/METADATA
wrapzor-0.1.24.dist-info/WHEEL
wrapzor-0.1.24.dist-info/entry_points.txt
wrapzor-0.1.24.dist-info/RECORD
