Metadata-Version: 2.1
Name: wrapzor
Version: 0.1.24
Summary: 
Author: flam
Author-email: florence.lam@tracktor.fr
Requires-Python: >=3.10,<4.0
Classifier: Programming Language :: Python :: 3
Classifier: Programming Language :: Python :: 3.10
Classifier: Programming Language :: Python :: 3.11
Provides-Extra: utils
Requires-Dist: httpx (>=0.24.1)
Requires-Dist: jupyterlab (>=3.4.6,<4.0.0) ; extra == "utils"
Requires-Dist: pandas (>=1.4.4,<2.0.0) ; extra == "utils"
Requires-Dist: piou (>=0.10.5,<1.0)
Requires-Dist: pydantic (>=1.9.2,<2.0.0)
Requires-Dist: seaborn (>=0.12.0,<0.13.0) ; extra == "utils"
